{
  "projects": [{
    "title": "SeaClouds",
    "subtitle": "Seamless adaptive multi-cloud management of service-based applications",
    "id": "EU-FP7-ICT-610531",
    "home": "http://seaclouds-project.eu/",
    "type": "eu"
  }, {
    "title": "Through the Fog",
    "subtitle": "Deploying, programming and supporting fog computing applications",
    "id": "PRA_2016_64",
    "home": "http://pages.di.unipi.it/throughthefog/",
    "type": "unipi"
  }, {
    "title": "AMaCA",
    "subtitle": "Automating the management of composite applications",
    "id": "POR-FSE 2014-2020",
    "home": "http://www.regione.toscana.it/bancadati/atti/Contenuto.xml?id=5155326&nomeFile=Decreto_n.11493_del_01-08-2017-Allegato-A",
    "type": "toscana"
  }]
}
